nlkit/__init__.py
nlkit/data.py
nlkit/layers.py
nlkit/metrics.py
nlkit/preprocessor.py
nlkit/stats.py
nlkit/trainer.py
nlkit/utils.py
nlkit/word2vec.py
nlkit-0.0.2rc2.dist-info/LICENSE
nlkit-0.0.2rc2.dist-info/METADATA
nlkit-0.0.2rc2.dist-info/WHEEL
nlkit-0.0.2rc2.dist-info/top_level.txt
nlkit-0.0.2rc2.dist-info/RECORD
