Metadata-Version: 2.1
Name: nlkit
Version: 0.0.2rc2
Summary: Easy to use nlp tools
Home-page: https://shihanmax.top
Author: shihanmax
Author-email: shihanmax@foxmail.com
License: MIT
Platform: UNKNOWN
Requires-Dist: numpy (>=1.17.0)
Requires-Dist: scipy (>=1.5.0)
Requires-Dist: matplotlib (>=3.0.0)
Requires-Dist: torch (>=1.2.0)
Requires-Dist: gensim (<=3.9.9)
Requires-Dist: rouge (>=1.0.0)
